googlesearcherror/__init__.py
googlesearcherror/googlesearcherror.py
googlesearcherror-0.0.2.dist-info/LICENCE
googlesearcherror-0.0.2.dist-info/METADATA
googlesearcherror-0.0.2.dist-info/WHEEL
googlesearcherror-0.0.2.dist-info/top_level.txt
googlesearcherror-0.0.2.dist-info/RECORD
