Metadata-Version: 2.1
Name: googlesearcherror
Version: 0.0.2
Summary: A package to search error in python code
Home-page: https://github.com/plantcraft94/pysearcherror
Author: plantcraft94
Classifier: Programming Language :: Python :: 3
Classifier: License :: OSI Approved :: MIT License
Classifier: Operating System :: OS Independent
Requires-Python: >=3.6
License-File: LICENCE
